litsandbox/__about__.py
litsandbox/__init__.py
litsandbox/code_inspect.py
litsandbox/py.typed
litsandbox/sandbox.py
litsandbox-0.0.1a0.dist-info/METADATA
litsandbox-0.0.1a0.dist-info/WHEEL
litsandbox-0.0.1a0.dist-info/licenses/LICENSE
litsandbox-0.0.1a0.dist-info/RECORD
