Metadata-Version: 2.4
Name: litsandbox
Version: 0.0.1a0
Summary: Safe and persistent environment for running AI generated code.
Project-URL: Homepage, https://github.com/Lightning-AI/litsandbox
Author-email: Lightning AI <community@lightning.ai>
License: Apache-2.0
License-File: LICENSE
Requires-Python: >=3.9
Requires-Dist: lightning-sdk>=0.2.23
Provides-Extra: dev
Requires-Dist: coverage>=7.9.1; extra == 'dev'
Requires-Dist: coverage[toml]>=7.5.3; extra == 'dev'
Requires-Dist: pytest-cov>=6.2.1; extra == 'dev'
Requires-Dist: pytest>=8.4.1; extra == 'dev'
